odoo10_addon_l10n_br_account_banking_payment-10.0.1.0.0.99.dev16-py2.7-nspkg.pth
odoo/addons/l10n_br_account_banking_payment/README.rst
odoo/addons/l10n_br_account_banking_payment/__init__.py
odoo/addons/l10n_br_account_banking_payment/__manifest__.py
odoo/addons/l10n_br_account_banking_payment/demo/account_banking_payment_demo.xml
odoo/addons/l10n_br_account_banking_payment/i18n/pt_BR.po
odoo/addons/l10n_br_account_banking_payment/models/__init__.py
odoo/addons/l10n_br_account_banking_payment/models/account_move_line.py
odoo/addons/l10n_br_account_banking_payment/models/account_payment.py
odoo/addons/l10n_br_account_banking_payment/readme/CONFIGURE.rst
odoo/addons/l10n_br_account_banking_payment/readme/CONTRIBUTORS.rst
odoo/addons/l10n_br_account_banking_payment/readme/CREDITS.rst
odoo/addons/l10n_br_account_banking_payment/readme/DESCRIPTION.rst
odoo/addons/l10n_br_account_banking_payment/readme/HISTORY.rst
odoo/addons/l10n_br_account_banking_payment/readme/INSTALL.rst
odoo/addons/l10n_br_account_banking_payment/readme/ROADMAP.rst
odoo/addons/l10n_br_account_banking_payment/readme/USAGE.rst
odoo/addons/l10n_br_account_banking_payment/static/description/icon.png
odoo/addons/l10n_br_account_banking_payment/static/description/index.html
odoo/addons/l10n_br_account_banking_payment/tests/__init__.py
odoo/addons/l10n_br_account_banking_payment/tests/test_payment_order.py
odoo/addons/l10n_br_account_banking_payment/views/account_due_list.xml
odoo/addons/l10n_br_account_banking_payment/views/account_payment.xml
odoo10_addon_l10n_br_account_banking_payment-10.0.1.0.0.99.dev16.dist-info/METADATA
odoo10_addon_l10n_br_account_banking_payment-10.0.1.0.0.99.dev16.dist-info/RECORD
odoo10_addon_l10n_br_account_banking_payment-10.0.1.0.0.99.dev16.dist-info/WHEEL
odoo10_addon_l10n_br_account_banking_payment-10.0.1.0.0.99.dev16.dist-info/namespace_packages.txt
odoo10_addon_l10n_br_account_banking_payment-10.0.1.0.0.99.dev16.dist-info/top_level.txt
