Metadata-Version: 2.1
Name: odoo10-addon-l10n-br-account-banking-payment
Version: 10.0.1.0.0.99.dev16
Summary: Brazilian Banking - Debit and Payments Export Infrastructure
Home-page: https://github.com/odoo-brazil/odoo-brazil-banking
Author: KMEE, Odoo Community Association (OCA)
Author-email: support@odoo-community.org
License: AGPL-3
Platform: UNKNOWN
Classifier: Programming Language :: Python
Classifier: Framework :: Odoo
Classifier: License :: OSI Approved :: GNU Affero General Public License v3
Requires-Python: ~=2.7
Requires-Dist: odoo10-addon-account-due-list
Requires-Dist: odoo10-addon-account-payment-order
Requires-Dist: odoo10-addon-l10n-br-account
Requires-Dist: odoo (<10.1dev,>=10.0)
